NowWeather.py
echidna/__init__.py
NowWeather-0.0.0.dist-info/METADATA
NowWeather-0.0.0.dist-info/WHEEL
NowWeather-0.0.0.dist-info/entry_points.txt
NowWeather-0.0.0.dist-info/top_level.txt
NowWeather-0.0.0.dist-info/RECORD
